{
  "project": {
    "__TYPE__": "GroupContentType",
    "value": [
      {
        "__TYPE__": "GroupItemContent",
        "value": [
          [
            "title",
            {
              "__TYPE__": "StructuredTextContent",
              "value": [
                {
                  "type": "paragraph",
                  "content": {
                    "text": "Id Lorem consectetur elit ipsum do ipsum ipsum laboris consequat anim amet anim eu duis. Aliqua consectetur exercitation consectetur est incididunt excepteur pariatur aliqua laborum ipsum quis."
                  }
                }
              ]
            }
          ],
          [
            "link",
            {
              "__TYPE__": "LinkContent",
              "value": {
                "__TYPE__": "ExternalLink",
                "url": "http://twitter.com"
              }
            }
          ],
          [
            "image",
            {
              "__TYPE__": "ImageContent",
              "origin": {
                "id": "main",
                "url": "https://images.unsplash.com/photo-1504198070170-4ca53bb1c1fa",
                "width": 2747,
                "height": 4120
              },
              "url": "https://images.unsplash.com/photo-1504198070170-4ca53bb1c1fa",
              "width": 2747,
              "height": 4120,
              "edit": {
                "zoom": 1,
                "crop": {
                  "x": 0,
                  "y": 0
                },
                "background": "transparent"
              },
              "thumbnails": {}
            }
          ],
          [
            "position",
            {
              "__TYPE__": "FieldContent",
              "value": "middle_top",
              "type": "Select"
            }
          ]
        ]
      }
    ]
  }
}